catsim_poly_debug.py
catsim/__init__.py
catsim/cat.py
catsim/estimation.py
catsim/initialization.py
catsim/irt.py
catsim/plot.py
catsim/selection.py
catsim/simulation.py
catsim/stopping.py
catsim_polytomous-0.0.1.dist-info/COPYING
catsim_polytomous-0.0.1.dist-info/COPYING.LESSER
catsim_polytomous-0.0.1.dist-info/METADATA
catsim_polytomous-0.0.1.dist-info/WHEEL
catsim_polytomous-0.0.1.dist-info/top_level.txt
catsim_polytomous-0.0.1.dist-info/RECORD
