Metadata-Version: 2.1
Name: catsim-polytomous
Version: 0.0.1
Summary: Computerized Adaptive Testing Simulator w/ support for polytomous items using the Partial Credit Model (PCM)
Author-email: Douglas De Rizzo Meneghetti <douglasrizzo@gmail.com>, Vaishak Krishna <vaishak.krishna@gmail.com>
License: GNU LESSER GENERAL PUBLIC LICENSE
Classifier: Development Status :: 4 - Beta
Classifier: Intended Audience :: Education
Classifier: Intended Audience :: Science/Research
Classifier: Natural Language :: English
Classifier: Programming Language :: Python :: 3.5
Classifier: Programming Language :: Python :: 3.6
Classifier: Programming Language :: Python :: 3.7
Classifier: Programming Language :: Python :: 3.8
Classifier: Topic :: Education :: Testing
Classifier: License :: OSI Approved :: GNU Lesser General Public License v3 (LGPLv3)
Requires-Python: >=3.5
License-File: COPYING
License-File: COPYING.LESSER
Requires-Dist: scipy
Requires-Dist: numexpr
Requires-Dist: matplotlib
Requires-Dist: scikit-learn
Requires-Dist: json-tricks
Requires-Dist: tqdm
Requires-Dist: numpy
Provides-Extra: dev
Requires-Dist: mypy ; extra == 'dev'
Requires-Dist: pylama ; extra == 'dev'
Requires-Dist: yapf ; extra == 'dev'
Requires-Dist: black ; extra == 'dev'
Requires-Dist: isort ; extra == 'dev'
Provides-Extra: docs
Requires-Dist: Sphinx ; extra == 'docs'
Requires-Dist: numpydoc ; extra == 'docs'
Requires-Dist: sphinx-autodoc-annotation ; extra == 'docs'
Requires-Dist: sphinx-rtd-theme ; extra == 'docs'
Requires-Dist: m2r2 ; extra == 'docs'
Requires-Dist: bibtex-pygments-lexer ; extra == 'docs'
Requires-Dist: matplotlib ; extra == 'docs'
Provides-Extra: testing
Requires-Dist: nose ; extra == 'testing'
Requires-Dist: nose-cov ; extra == 'testing'
Requires-Dist: sklearn ; extra == 'testing'
Requires-Dist: flake8 ; extra == 'testing'
Requires-Dist: yapf ; extra == 'testing'
Provides-Extra: upload
Requires-Dist: twine ; extra == 'upload'
Requires-Dist: build ; extra == 'upload'
